pfip/__init__.py
pfip/base/__init__.py
pfip/base/constant.py
pfip/base/errors.py
pfip/base/parser/__init__.py
pfip/base/parser/base.py
pfip/base/parser/parser_model.py
pfip/base/parser/repair.py
pfip/base/splitter/__init__.py
pfip/base/splitter/base.py
pfip/base/splitter/recursive_splitter.py
pfip/base/splitter/sentence_splitter.py
pfip/base/splitter/splitter_model.py
pfip/base/splitter/title_splitter.py
pfip/base/util/__init__.py
pfip/base/util/character_splitter.py
pfip/base/util/common.py
pfip/base/util/file_util.py
pfip/base/util/generator_id.py
pfip/base/util/kangxi2chinese.py
pfip/base/util/rectangle.py
pfip/base/util/str_util.py
pfip/excel/__init__.py
pfip/excel/excel_parser.py
pfip/md/__init__.py
pfip/md/md_ele_handler.py
pfip/md/md_parser.py
pfip/pdf/__init__.py
pfip/pdf/analyse/__init__.py
pfip/pdf/analyse/base.py
pfip/pdf/analyse/footer_analyser.py
pfip/pdf/analyse/header_analyser.py
pfip/pdf/analyse/pdf_analyser.py
pfip/pdf/analyse/pdf_type_analyser.py
pfip/pdf/analyse/valid_page_analyser.py
pfip/pdf/pdf_splitter.py
pfip/pdf/proxy_pdf_parser.py
pfip/pdf/scanned/__init__.py
pfip/pdf/scanned/scanned_pdf_ele_handler.py
pfip/pdf/scanned/scanned_pdf_parser.py
pfip/pdf/scanned/scanned_pdf_result_repair.py
pfip/pdf/text/__init__.py
pfip/pdf/text/text_pdf_ele_handler.py
pfip/pdf/text/text_pdf_parser.py
pfip/pdf/text/text_pdf_result_repair.py
pfip/pdf/title/__init__.py
pfip/pdf/title/base.py
pfip/pdf/title/bookmark_title.py
pfip/pdf/title/layout_analysis_title.py
pfip/pdf/title/title_item_connector.py
pfip/pdf/title/toc_page_title.py
pfip/pfip.py
pfip/ppt/__init__.py
pfip/ppt/ppt_ele_handler.py
pfip/ppt/ppt_parser.py
pfip/ppt/ppt_result_repair.py
pfip/txt/__init__.py
pfip/txt/txt_parser.py
pfip/web/__init__.py
pfip/web/html_parser.py
pfip/word/__init__.py
pfip/word/auto_num_helper.py
pfip/word/word_ele_handler.py
pfip/word/word_parser.py
pfip/word/word_result_repair.py
pfip-9.1.25.dist-info/METADATA
pfip-9.1.25.dist-info/WHEEL
pfip-9.1.25.dist-info/RECORD
